{
  "0": [
    [
      39,
      16
    ],
    [
      39,
      17
    ],
    [
      44,
      16
    ],
    [
      47,
      29
    ],
    [
      42,
      30
    ],
    [
      43,
      32
    ],
    [
      16,
      36
    ],
    [
      16,
      35
    ],
    [
      12,
      19
    ],
    [
      36,
      16
    ],
    [
      39,
      16
    ]
  ],
  "1": [
    [
      135,
      133
    ],
    [
      158,
      199
    ],
    [
      109,
      209
    ],
    [
      104,
      196
    ],
    [
      104,
      194
    ],
    [
      94,
      167
    ],
    [
      84,
      169
    ],
    [
      78,
      151
    ],
    [
      88,
      149
    ],
    [
      85,
      143
    ],
    [
      135,
      133
    ]
  ],
  "2": [
    [
      53,
      133
    ],
    [
      31,
      136
    ],
    [
      31,
      135
    ],
    [
      30,
      129
    ],
    [
      29,
      127
    ],
    [
      52,
      125
    ],
    [
      53,
      133
    ]
  ],
  "3": [
    [
      73,
      99
    ],
    [
      54,
      103
    ],
    [
      53,
      101
    ],
    [
      51,
      95
    ],
    [
      50,
      93
    ],
    [
      69,
      89
    ],
    [
      73,
      99
    ]
  ],
  "4": [
    [
      67,
      86
    ],
    [
      50,
      89
    ],
    [
      50,
      89
    ],
    [
      47,
      80
    ],
    [
      50,
      80
    ],
    [
      65,
      77
    ],
    [
      67,
      86
    ]
  ]
}