<annotation><filename>317.jpg</filename><size><width>228</width><height>228</height><depth>3</depth></size><object><name>building</name><bndbox><xmin>108.0</xmin><ymin>196.0</ymin><xmax>147.0</xmax><ymax>233.0</ymax></bndbox></object><object><name>building</name><bndbox><xmin>73.0</xmin><ymin>82.0</ymin><xmax>118.0</xmax><ymax>108.0</ymax></bndbox></object><object><name>building</name><bndbox><xmin>4.0</xmin><ymin>176.0</ymin><xmax>48.0</xmax><ymax>204.0</ymax></bndbox></object><object><name>building</name><bndbox><xmin>201.0</xmin><ymin>6.0</ymin><xmax>239.0</xmax><ymax>30.0</ymax></bndbox></object><object><name>building</name><bndbox><xmin>30.0</xmin><ymin>98.0</ymin><xmax>53.0</xmax><ymax>115.0</ymax></bndbox></object><object><name>building</name><bndbox><xmin>7.0</xmin><ymin>-5.0</ymin><xmax>27.0</xmax><ymax>7.0</ymax></bndbox></object><object><name>building</name><bndbox><xmin>-17.0</xmin><ymin>102.0</ymin><xmax>18.0</xmax><ymax>127.0</ymax></bndbox></object><object><name>building</name><bndbox><xmin>73.0</xmin><ymin>185.0</ymin><xmax>88.0</xmax><ymax>201.0</ymax></bndbox></object><object><name>building</name><bndbox><xmin>94.0</xmin><ymin>162.0</ymin><xmax>130.0</xmax><ymax>190.0</ymax></bndbox></object><object><name>building</name><bndbox><xmin>30.0</xmin><ymin>83.0</ymin><xmax>51.0</xmax><ymax>95.0</ymax></bndbox></object><object><name>building</name><bndbox><xmin>15.0</xmin><ymin>31.0</ymin><xmax>34.0</xmax><ymax>40.0</ymax></bndbox></object><object><name>building</name><bndbox><xmin>52.0</xmin><ymin>174.0</ymin><xmax>65.0</xmax><ymax>188.0</ymax></bndbox></object><object><name>building</name><bndbox><xmin>70.0</xmin><ymin>-9.0</ymin><xmax>102.0</xmax><ymax>18.0</ymax></bndbox></object><object><name>building</name><bndbox><xmin>77.0</xmin><ymin>31.0</ymin><xmax>113.0</xmax><ymax>67.0</ymax></bndbox></object></annotation>