<annotation><filename>98.jpg</filename><size><width>228</width><height>228</height><depth>3</depth></size><object><name>building</name><bndbox><xmin>84.0</xmin><ymin>183.0</ymin><xmax>137.0</xmax><ymax>210.0</ymax></bndbox></object><object><name>building</name><bndbox><xmin>93.0</xmin><ymin>92.0</ymin><xmax>138.0</xmax><ymax>114.0</ymax></bndbox></object><object><name>building</name><bndbox><xmin>85.0</xmin><ymin>31.0</ymin><xmax>132.0</xmax><ymax>69.0</ymax></bndbox></object><object><name>building</name><bndbox><xmin>-14.0</xmin><ymin>87.0</ymin><xmax>24.0</xmax><ymax>116.0</ymax></bndbox></object><object><name>building</name><bndbox><xmin>54.0</xmin><ymin>36.0</ymin><xmax>75.0</xmax><ymax>51.0</ymax></bndbox></object><object><name>building</name><bndbox><xmin>6.0</xmin><ymin>55.0</ymin><xmax>26.0</xmax><ymax>70.0</ymax></bndbox></object><object><name>building</name><bndbox><xmin>26.0</xmin><ymin>183.0</ymin><xmax>59.0</xmax><ymax>207.0</ymax></bndbox></object><object><name>building</name><bndbox><xmin>56.0</xmin><ymin>-3.0</ymin><xmax>79.0</xmax><ymax>9.0</ymax></bndbox></object><object><name>building</name><bndbox><xmin>34.0</xmin><ymin>56.0</ymin><xmax>54.0</xmax><ymax>70.0</ymax></bndbox></object><object><name>building</name><bndbox><xmin>36.0</xmin><ymin>90.0</ymin><xmax>64.0</xmax><ymax>115.0</ymax></bndbox></object><object><name>building</name><bndbox><xmin>7.0</xmin><ymin>13.0</ymin><xmax>32.0</xmax><ymax>47.0</ymax></bndbox></object></annotation>